uffd/__init__.py
uffd/babel.cfg
uffd/csrf.py
uffd/database.py
uffd/default_config.cfg
uffd/fido2_compat.py
uffd/navbar.py
uffd/password_hash.py
uffd/remailer.py
uffd/secure_redirect.py
uffd/sendmail.py
uffd/tasks.py
uffd/template_helper.py
uffd/utils.py
uffd/commands/__init__.py
uffd/commands/cleanup.py
uffd/commands/gendevcert.py
uffd/commands/group.py
uffd/commands/profile.py
uffd/commands/role.py
uffd/commands/roles_update_all.py
uffd/commands/unique_email_addresses.py
uffd/commands/user.py
uffd/migrations/README.md
uffd/migrations/alembic.ini
uffd/migrations/env.py
uffd/migrations/script.py.mako
uffd/migrations/versions/042879d5e3ac_lower_case_mail_receive_addresses.py
uffd/migrations/versions/09d2edcaf0cc_add_expires_attribute_to_ratelimit_event.py
uffd/migrations/versions/11ecc8f1ac3b_mysql_compat_fixes.py
uffd/migrations/versions/23293f32b503_deactivate_users.py
uffd/migrations/versions/2a6b1fb82ce6_added_missing_oauth2grant_code_index.py
uffd/migrations/versions/2b68f688bec1_remailer_v2.py
uffd/migrations/versions/468995a9c9ee_unique_email_addresses.py
uffd/migrations/versions/54b2413586fd_invite_pk_change.py
uffd/migrations/versions/5a07d4a63b64_role_inclusion.py
uffd/migrations/versions/5cab70e95bf8_invite_creator_and_role_moderator_group.py
uffd/migrations/versions/704d1245331c_remailer_setting_and_api_permission.py
uffd/migrations/versions/878b25c4fae7_ldap_to_db.py
uffd/migrations/versions/9f824f61d8ac_use_utc_for_datetime.py
uffd/migrations/versions/a29870f95175_initial_migration.py
uffd/migrations/versions/a594d3b3e05b_added_role_locked.py
uffd/migrations/versions/a60ce68b9214_fix_not_null_on_role_groups_group_id.py
uffd/migrations/versions/a8c6b6e91c28_device_login.py
uffd/migrations/versions/a9b449776953_add_mfa_method_totp_last_counter.py
uffd/migrations/versions/aeb07202a6c8_locking_and_new_id_allocation.py
uffd/migrations/versions/af07cea65391_unified_password_hashing_for_user_and_signup.py
uffd-2.3.1.dist-info/LICENSE
uffd-2.3.1.dist-info/METADATA
uffd-2.3.1.dist-info/WHEEL
uffd-2.3.1.dist-info/top_level.txt
uffd-2.3.1.dist-info/RECORD
