Metadata-Version: 2.1
Name: uffd
Version: 2.3.1
Summary: Web-based user management and single sign-on software
Home-page: https://git.cccv.de/uffd/uffd
Author: CCCV
Author-email: it@cccv.de
License: AGPL3
Classifier: Programming Language :: Python :: 3
Classifier: Development Status :: 5 - Production/Stable
Classifier: License :: OSI Approved :: GNU Affero General Public License v3 or later (AGPLv3+)
Classifier: Operating System :: OS Independent
Classifier: Topic :: System :: Systems Administration :: Authentication/Directory :: LDAP
Classifier: Topic :: Internet :: WWW/HTTP :: Dynamic Content
Classifier: Environment :: Web Environment
Classifier: Framework :: Flask
Requires-Python: >=3.7
License-File: LICENSE
Requires-Dist: flask ==1.0.2
Requires-Dist: Flask-SQLAlchemy ==2.1
Requires-Dist: qrcode ==6.1
Requires-Dist: fido2 ==0.5.0
Requires-Dist: oauthlib ==2.1.0
Requires-Dist: Flask-Migrate ==2.1.1
Requires-Dist: Flask-Babel ==0.11.2
Requires-Dist: alembic ==1.0.0
Requires-Dist: argon2-cffi ==18.3.0
Requires-Dist: itsdangerous ==0.24
Requires-Dist: prometheus-client ==0.9
Requires-Dist: certifi ==2018.8.24
Requires-Dist: cffi
Requires-Dist: chardet ==3.0.4
Requires-Dist: click ==7.0
Requires-Dist: cryptography ==2.6.1
Requires-Dist: idna ==2.6
Requires-Dist: Jinja2 ==2.10
Requires-Dist: MarkupSafe ==1.1.0
Requires-Dist: pyasn1 ==0.4.2
Requires-Dist: pycparser ==2.19
Requires-Dist: requests ==2.21.0
Requires-Dist: requests-oauthlib ==1.0.0
Requires-Dist: six ==1.12.0
Requires-Dist: SQLAlchemy ==1.2.18
Requires-Dist: urllib3 ==1.24.1
Requires-Dist: Werkzeug ==0.14.1
Requires-Dist: python-dateutil ==2.7.3
Requires-Dist: Mako ==1.0.7
